togather_event_sdk/__init__.py
togather_event_sdk/admin/__init__.py
togather_event_sdk/admin/v1/__init__.py
togather_event_sdk/admin/v1/admin_account_created_pb2.py
togather_event_sdk/admin/v1/admin_account_created_pb2.pyi
togather_event_sdk/admin/v1/admin_email_verification_requested_pb2.py
togather_event_sdk/admin/v1/admin_email_verification_requested_pb2.pyi
togather_event_sdk/common/__init__.py
togather_event_sdk/common/v1/__init__.py
togather_event_sdk/common/v1/event_envelop_pb2.py
togather_event_sdk/common/v1/event_envelop_pb2.pyi
togather_event_sdk/experience/__init__.py
togather_event_sdk/experience/v1/__init__.py
togather_event_sdk/experience/v1/category_pb2.py
togather_event_sdk/experience/v1/category_pb2.pyi
togather_event_sdk/experience/v1/experience_created_pb2.py
togather_event_sdk/experience/v1/experience_created_pb2.pyi
togather_event_sdk/experience/v1/tag_pb2.py
togather_event_sdk/experience/v1/tag_pb2.pyi
togather_event_sdk/partner/__init__.py
togather_event_sdk/partner/v1/__init__.py
togather_event_sdk/partner/v1/parter_account_created_pb2.py
togather_event_sdk/partner/v1/parter_account_created_pb2.pyi
togather_event_sdk/partner/v1/partner_application_rejected_pb2.py
togather_event_sdk/partner/v1/partner_application_rejected_pb2.pyi
togather_event_sdk/partner/v1/partner_emai_verification_requested_pb2.py
togather_event_sdk/partner/v1/partner_emai_verification_requested_pb2.pyi
togather_event_sdk/partner/v1/partner_profile_created_pb2.py
togather_event_sdk/partner/v1/partner_profile_created_pb2.pyi
togather_event_sdk/user/__init__.py
togather_event_sdk/user/v1/__init__.py
togather_event_sdk/user/v1/user_account_created_pb2.py
togather_event_sdk/user/v1/user_account_created_pb2.pyi
togather_event_sdk/user/v1/user_email_verification_requested_pb2.py
togather_event_sdk/user/v1/user_email_verification_requested_pb2.pyi
togather_event_sdk/user/v1/user_forgot_password_pb2.py
togather_event_sdk/user/v1/user_forgot_password_pb2.pyi
togather_event_sdk-1.0.51.dist-info/METADATA
togather_event_sdk-1.0.51.dist-info/WHEEL
togather_event_sdk-1.0.51.dist-info/top_level.txt
togather_event_sdk-1.0.51.dist-info/RECORD
