Metadata-Version: 2.4
Name: togather-event-sdk
Version: 1.0.51
Summary: Shared Protobuf event schemas for toGather microservices
Author: toGather team
License-Expression: ISC
Project-URL: Homepage, https://github.com/CrossroadsAcademy/togather-shared-events
Requires-Python: >=3.8
Requires-Dist: protobuf<7.0.0,>=6.0.0
